<?xml version="1.0" encoding="utf-8" ?>
<Defs>

	<ThingDef ParentName="OutlandApparelMakeableBase">
		<defName>Outland_ShoulderCloak</defName>
		<label>shoulder cloak</label>
		<description>A tough cloak to protect against heat, cold and some damage protection.</description>
		<techLevel>Medieval</techLevel>
		<graphicData>
			<texPath>Outland/Apparel/ShoulderCloak/Apparel</texPath>
			<graphicClass>Graphic_Single</graphicClass>
		</graphicData>
		<costStuffCount>80</costStuffCount>
		<stuffCategories>
			<li>Fabric</li>
			<li>Leathery</li>
		</stuffCategories>
		<statBases>
			<MaxHitPoints>200</MaxHitPoints>
			<WorkToMake>5000</WorkToMake>
			<Mass>2.15</Mass>
			<StuffEffectMultiplierArmor>0.35</StuffEffectMultiplierArmor>
			<StuffEffectMultiplierInsulation_Cold>0.80</StuffEffectMultiplierInsulation_Cold>
			<StuffEffectMultiplierInsulation_Heat>0.30</StuffEffectMultiplierInsulation_Heat>
			<EquipDelay>1.5</EquipDelay>
		</statBases>
		<apparel>
			<bodyPartGroups>
				<li>Torso</li>
				<li>Neck</li>
				<li>Shoulders</li>
				<li>Arms</li>
			</bodyPartGroups>
			<wornGraphicPath>Outland/Apparel/ShoulderCloak/Apparel</wornGraphicPath>
			<layers>
				<li>Shell</li>
			</layers>
			<tags>
				<li>Medieval</li>
				<li>MedievalBasic</li>
			</tags>
			<defaultOutfitTags>
				<li>Worker</li>
			</defaultOutfitTags>
		</apparel>
	</ThingDef>
	
</Defs>
